odoo10_addon_base_external_dbsource-10.0.2.0.0-py2.7-nspkg.pth
odoo/addons/base_external_dbsource/__manifest__.py
odoo/addons/base_external_dbsource/__init__.py
odoo/addons/base_external_dbsource/exceptions.py
odoo/addons/base_external_dbsource/README.rst
odoo/addons/base_external_dbsource/security/ir.model.access.csv
odoo/addons/base_external_dbsource/models/__init__.py
odoo/addons/base_external_dbsource/models/base_external_dbsource.py
odoo/addons/base_external_dbsource/i18n/ja.po
odoo/addons/base_external_dbsource/i18n/lv.po
odoo/addons/base_external_dbsource/i18n/zh_CN.po
odoo/addons/base_external_dbsource/i18n/nb_NO.po
odoo/addons/base_external_dbsource/i18n/uk.po
odoo/addons/base_external_dbsource/i18n/es_AR.po
odoo/addons/base_external_dbsource/i18n/ko.po
odoo/addons/base_external_dbsource/i18n/ru.po
odoo/addons/base_external_dbsource/i18n/gl_ES.po
odoo/addons/base_external_dbsource/i18n/pt.po
odoo/addons/base_external_dbsource/i18n/fr_CH.po
odoo/addons/base_external_dbsource/i18n/it.po
odoo/addons/base_external_dbsource/i18n/es.po
odoo/addons/base_external_dbsource/i18n/nl_BE.po
odoo/addons/base_external_dbsource/i18n/ar.po
odoo/addons/base_external_dbsource/i18n/lt.po
odoo/addons/base_external_dbsource/i18n/vi_VN.po
odoo/addons/base_external_dbsource/i18n/ro.po
odoo/addons/base_external_dbsource/i18n/tr.po
odoo/addons/base_external_dbsource/i18n/sr.po
odoo/addons/base_external_dbsource/i18n/es_PY.po
odoo/addons/base_external_dbsource/i18n/mk.po
odoo/addons/base_external_dbsource/i18n/hr.po
odoo/addons/base_external_dbsource/i18n/bg.po
odoo/addons/base_external_dbsource/i18n/es_EC.po
odoo/addons/base_external_dbsource/i18n/zh_TW.po
odoo/addons/base_external_dbsource/i18n/hu.po
odoo/addons/base_external_dbsource/i18n/fr_CA.po
odoo/addons/base_external_dbsource/i18n/gl.po
odoo/addons/base_external_dbsource/i18n/lt_LT.po
odoo/addons/base_external_dbsource/i18n/ca.po
odoo/addons/base_external_dbsource/i18n/id.po
odoo10_addon_base_external_dbsource-10.0.2.0.0.dist-info/top_level.txt
odoo10_addon_base_external_dbsource-10.0.2.0.0.dist-info/WHEEL
odoo10_addon_base_external_dbsource-10.0.2.0.0.dist-info/RECORD
odoo10_addon_base_external_dbsource-10.0.2.0.0.dist-info/metadata.json
odoo10_addon_base_external_dbsource-10.0.2.0.0.dist-info/DESCRIPTION.rst
odoo10_addon_base_external_dbsource-10.0.2.0.0.dist-info/METADATA
odoo10_addon_base_external_dbsource-10.0.2.0.0.dist-info/namespace_packages.txt
